forecast_solar_plants_calgary/__init__.py
forecast_solar_plants_calgary-0.1.0.dist-info/METADATA
forecast_solar_plants_calgary-0.1.0.dist-info/WHEEL
forecast_solar_plants_calgary-0.1.0.dist-info/RECORD
